PyBreathParams/__init__.py
PyBreathParams/activity_classifier.py
PyBreathParams/get_breath_params.py
PyBreathParams/ie_classifier.py
PyBreathParams/model_ar.joblib
PyBreathParams/model_ie.joblib
pybreathparams-1.0.4.dist-info/licenses/LICENSE
pybreathparams-1.0.4.dist-info/METADATA
pybreathparams-1.0.4.dist-info/WHEEL
pybreathparams-1.0.4.dist-info/top_level.txt
pybreathparams-1.0.4.dist-info/RECORD
